abhi/__init__.py
abhi/flutter_codes.py
abhi/flutter_topics.py
abhi77-0.6.dist-info/LICENSE
abhi77-0.6.dist-info/METADATA
abhi77-0.6.dist-info/WHEEL
abhi77-0.6.dist-info/top_level.txt
abhi77-0.6.dist-info/RECORD
