Metadata-Version: 2.2
Name: abhi77
Version: 0.6
Summary: Flutter syllabus and example codes package
Author: Abhishek Yadav
License: MIT
License-File: LICENSE
Dynamic: author
Dynamic: license
Dynamic: summary
